<?xml version="1.0" encoding="UTF-8" standalone="no"?><publications xmlns="http://www.example.com/publications" xmlns:xs="http://www.w3.org/2001/XMLSchema"><FictionLiterature id="1"><name>Les Miserables</name><year>2013</year><pagesNumber>1221</pagesNumber><author>Victor Hugo</author><genre>historical novel</genre></FictionLiterature><FictionLiterature id="2"><name>The Great Gatsby</name><year>2016</year><pagesNumber>198</pagesNumber><author>F.Scott Fitzgerald</author><genre>historical fiction</genre></FictionLiterature><FictionLiterature id="3"><name>Fahrenheit 451</name><year>2004</year><pagesNumber>208</pagesNumber><author>Ray Bradbury</author><genre>science fiction</genre></FictionLiterature><Magazine id="4"><name>National Geographic</name><year>2018</year><pagesNumber>158</pagesNumber><audience>ANY</audience><number>2</number><periodicity>MONTHLY</periodicity></Magazine><FictionLiterature id="5"><name>The Dark Tower</name><year>2003</year><pagesNumber>336</pagesNumber><author>Stephen King</author><volumesNumber>5</volumesNumber><volumeNumber>1</volumeNumber><genre>dark fantasy</genre></FictionLiterature><FictionLiterature id="6"><name>The Dark Tower</name><year>2006</year><pagesNumber>496</pagesNumber><author>Stephen King</author><volumesNumber>5</volumesNumber><volumeNumber>2</volumeNumber><genre>dark fantasy</genre></FictionLiterature><FictionLiterature id="7"><name>The Dark Tower</name><year>2012</year><pagesNumber>670</pagesNumber><author>Stephen King</author><volumesNumber>5</volumesNumber><volumeNumber>3</volumeNumber><genre>dark fantasy</genre></FictionLiterature><Dictionary id="8"><name>Mandarin Chinese </name><year>2007</year><pagesNumber>671</pagesNumber><author/><type>BILINGUAL</type><publishers>Berlitz</publishers></Dictionary><Magazine id="9"><name>National Geographic</name><year>2018</year><pagesNumber>165</pagesNumber><audience>ANY</audience><number>12</number><periodicity>MONTHLY</periodicity></Magazine><Manuale id="10"><name>German for dummies</name><year>2000</year><pagesNumber>384</pagesNumber><author>Paulina Christensen, Wendy Foster, Anne Fox</author><field>linguistics</field><audience>BEGINNER</audience></Manuale></publications>